ultimate_hosts_blacklist/helpers/__init__.py
ultimate_hosts_blacklist/helpers/command.py
ultimate_hosts_blacklist/helpers/dict.py
ultimate_hosts_blacklist/helpers/directory.py
ultimate_hosts_blacklist/helpers/download.py
ultimate_hosts_blacklist/helpers/file.py
ultimate_hosts_blacklist/helpers/list.py
ultimate_hosts_blacklist/helpers/our_process_wrapper.py
ultimate_hosts_blacklist/helpers/regex.py
ultimate_hosts_blacklist/helpers/travis_ci.py
ultimate_hosts_blacklist_helpers-1.20.1.dist-info/LICENSE
ultimate_hosts_blacklist_helpers-1.20.1.dist-info/METADATA
ultimate_hosts_blacklist_helpers-1.20.1.dist-info/WHEEL
ultimate_hosts_blacklist_helpers-1.20.1.dist-info/top_level.txt
ultimate_hosts_blacklist_helpers-1.20.1.dist-info/RECORD
