Metadata-Version: 2.1
Name: ultimate-hosts-blacklist-helpers
Version: 1.20.1
Summary: The helpers classes/functions of the Ultimate Hosts Blacklist project.
Home-page: https://github.com/Ultimate-Hosts-Blacklist/dev-center/tree/helpers
Author: UNKNOWN
Author-email: UNKNOWN
License: MIT
Keywords: Python,helpers
Platform: any
Classifier: Environment :: Console
Classifier: Topic :: Internet
Classifier: Development Status :: 5 - Production/Stable
Classifier: Intended Audience :: Developers
Classifier: Programming Language :: Python
Classifier: Programming Language :: Python :: 3
Classifier: License :: OSI Approved :: MIT License
Requires-Dist: requests
Requires-Dist: pyyaml
